xpytools/__init__.py
xpytools/xdeco/__init__.py
xpytools/xdeco/asSingleton.py
xpytools/xdeco/requireModules.py
xpytools/xtool/__init__.py
xpytools/xtool/df/__init__.py
xpytools/xtool/df/_handlers.py
xpytools/xtool/df/lookup.py
xpytools/xtool/df/merge_fill.py
xpytools/xtool/df/normalize_column_names.py
xpytools/xtool/df/replace_none_like.py
xpytools/xtool/img/__init__.py
xpytools/xtool/img/conversions.py
xpytools/xtool/img/load.py
xpytools/xtool/img/transform.py
xpytools/xtool/sql/__init__.py
xpytools/xtool/sql/prepare_dataframe.py
xpytools/xtool/sql/to_pg_array.py
xpytools/xtool/txt/__init__.py
xpytools/xtool/txt/clean.py
xpytools/xtool/txt/pad.py
xpytools/xtool/txt/split_lines.py
xpytools/xtool/txt/strip_ascii.py
xpytools/xtool/txt/strip_html.py
xpytools/xtool/txt/truncate.py
xpytools/xtool/xpyt_pydantic/TypeSafeAccessMixin.py
xpytools/xtool/xpyt_pydantic/__init__.py
xpytools/xtype/TTLSet.py
xpytools/xtype/UUIDLike.py
xpytools/xtype/__init__.py
xpytools/xtype/common.py
xpytools/xtype/choice/_LiteralEnumType.py
xpytools/xtype/choice/__init__.py
xpytools/xtype/choice/anyChoice.py
xpytools/xtype/choice/floatChoice.py
xpytools/xtype/choice/intChoice.py
xpytools/xtype/choice/strChoice.py
xpytools/xtype/xcast/__init__.py
xpytools/xtype/xcast/complex.py
xpytools/xtype/xcast/dataframe.py
xpytools/xtype/xcast/datetime.py
xpytools/xtype/xcast/json.py
xpytools/xtype/xcast/null.py
xpytools/xtype/xcast/primitives.py
xpytools/xtype/xcast/to_primitives.py
xpytools/xtype/xcheck/__init__.py
xpytools/xtype/xcheck/base64.py
xpytools/xtype/xcheck/complex.py
xpytools/xtype/xcheck/dataframe.py
xpytools/xtype/xcheck/datetime.py
xpytools/xtype/xcheck/is_empty.py
xpytools/xtype/xcheck/json.py
xpytools/xtype/xcheck/null.py
xpytools/xtype/xcheck/primitives.py
xpytools/xtype/xcheck/uuid.py
xpytools-1.0.0.dist-info/METADATA
xpytools-1.0.0.dist-info/WHEEL
xpytools-1.0.0.dist-info/licenses/LICENSE
xpytools-1.0.0.dist-info/RECORD
