Metadata-Version: 2.4
Name: xpytools
Version: 1.0.0
Summary: Python utilities for safe type handling, data manipulation, and runtime validation.
Project-URL: Homepage, https://github.com/Kydoimos97/xpytools
Project-URL: Author GitHub, https://github.com/Kydoimos97
Project-URL: Author PyPI, https://pypi.org/user/Kydoimos97/
Project-URL: PyPI, https://pypi.org/project/xpytools/
Author-email: Kydoimos97 <willemvanderschans97+dev@gmail.com>
License: MIT License
License-File: LICENSE
Classifier: Intended Audience :: Developers
Classifier: License :: OSI Approved :: MIT License
Classifier: Operating System :: OS Independent
Classifier: Programming Language :: Python :: 3
Classifier: Programming Language :: Python :: 3.11
Requires-Python: >=3.11
